{
  "personal": {
    "name": "Landry Kongbo",
    "title": "Développeur Full-Stack",
    "bio": "Je construis des applications web qui tiennent debout là où le réseau ne tient pas. Neuf ans à Bangui, à faire tourner du logiciel utile dans des conditions difficiles.",
    "photo": "",
    "email": "landry.kongbo@exemple.cf",
    "phone": "+236 72 45 18 90",
    "location": "Bangui, République centrafricaine",
    "resumeUrl": ""
  },
  "hero": {
    "subtitle": "Je conçois des outils pensés pour le terrain : légers, utilisables hors ligne, et compréhensibles dès la première fois. La contrainte n'est pas un handicap, c'est ce qui force à faire simple.",
    "typedWords": [
      "Développeur Full-Stack",
      "Spécialiste hors-ligne",
      "Vue.js & TypeScript",
      "Bangui, Centrafrique"
    ],
    "ctaText": "Voir mes projets",
    "ctaLink": "#projects",
    "ctaSecondaryText": "Me contacter",
    "ctaSecondaryLink": "#contact",
    "background": "gradient",
    "backgroundMedia": ""
  },
  "about": {
    "enabled": true,
    "title": "À propos",
    "subtitle": "Qui je suis, et comment je travaille",
    "content": "<p>J'ai appris à programmer au cyber de l'avenue Boganda, en partageant une connexion avec quinze personnes. Cette contrainte a façonné toute ma façon de travailler : si une page met dix secondes à s'afficher, elle ne sert à personne.</p>\n<p>Aujourd'hui je conçois des applications pour des ONG, des coopératives et des administrations en Centrafrique. Le point commun de ces projets : ils doivent fonctionner sur un téléphone d'entrée de gamme, avec une connexion qui disparaît sans prévenir, et être pris en main par quelqu'un qui n'a jamais utilisé de logiciel métier.</p>\n<p>Je travaille surtout avec <strong>Vue 3</strong>, <strong>TypeScript</strong> et <strong>Node.js</strong>, avec une attention particulière au <strong>fonctionnement hors ligne</strong> et au poids réel des pages. Je choisis l'outil selon le problème — jamais l'inverse.</p>",
    "image": "",
    "values": [
      "Ce qui ne marche pas hors ligne ne marche pas",
      "Chaque kilo-octet se paie en crédit téléphonique",
      "Un outil qu'on doit expliquer est un outil raté",
      "Livrer vaut mieux que perfectionner"
    ]
  },
  "stats": {
    "enabled": true,
    "title": "En chiffres",
    "subtitle": "",
    "items": [
      {
        "id": "4d79df97-8666-4a26-bdf9-f0ca557d2001",
        "order": 0,
        "enabled": true,
        "archived": false,
        "label": "Années d'expérience",
        "value": 9,
        "suffix": "",
        "icon": "hourglass"
      },
      {
        "id": "483e8b05-8e7a-4d7d-8aea-e05b4bda43e7",
        "order": 1,
        "enabled": true,
        "archived": false,
        "label": "Projets livrés",
        "value": 41,
        "suffix": "",
        "icon": "rocket"
      },
      {
        "id": "0f7f794f-2392-4136-8451-6a62f1ce78ca",
        "order": 2,
        "enabled": true,
        "archived": false,
        "label": "Organisations accompagnées",
        "value": 18,
        "suffix": "",
        "icon": "handshake"
      },
      {
        "id": "54ebcc6b-215f-4499-865f-6bafa058c940",
        "order": 3,
        "enabled": true,
        "archived": false,
        "label": "Développeurs formés",
        "value": 60,
        "suffix": "+",
        "icon": "heart"
      }
    ]
  },
  "skills": {
    "enabled": true,
    "title": "Compétences",
    "subtitle": "Les outils que je maîtrise vraiment",
    "categories": [
      {
        "id": "ea044d35-0492-4b96-9afb-80e4b051ccaa",
        "order": 0,
        "enabled": true,
        "archived": false,
        "name": "Front-end",
        "icon": "palette",
        "skills": [
          {
            "id": "5b659f64-4284-41af-8dd2-557dbde1de49",
            "name": "Vue.js 3",
            "level": "Expert",
            "score": 94,
            "icon": "",
            "order": 0
          },
          {
            "id": "20f9c730-3aec-4b0a-8e71-d8bb08a7c440",
            "name": "TypeScript",
            "level": "Senior",
            "score": 88,
            "icon": "",
            "order": 1
          },
          {
            "id": "3b79df60-8313-45c2-a2bc-978b789b1983",
            "name": "PWA & hors-ligne",
            "level": "Expert",
            "score": 92,
            "icon": "",
            "order": 2
          },
          {
            "id": "a5e69bda-5d97-4720-8df6-17ea5a240efe",
            "name": "CSS / Tailwind",
            "level": "Senior",
            "score": 86,
            "icon": "",
            "order": 3
          },
          {
            "id": "1dfc2414-c65a-4f68-9f6f-321fd3820119",
            "name": "Accessibilité (WCAG)",
            "level": "Mid",
            "score": 70,
            "icon": "",
            "order": 4
          }
        ]
      },
      {
        "id": "6640f39a-51f7-4b5e-9713-8c2bf955cfaa",
        "order": 1,
        "enabled": true,
        "archived": false,
        "name": "Back-end",
        "icon": "settings",
        "skills": [
          {
            "id": "e30365d8-7fa9-4e7b-89e4-e59307f3a3b8",
            "name": "Node.js",
            "level": "Senior",
            "score": 87,
            "icon": "",
            "order": 0
          },
          {
            "id": "8f3e7ba3-5571-469a-a2ec-d40d41414a79",
            "name": "PHP / Laravel",
            "level": "Senior",
            "score": 84,
            "icon": "",
            "order": 1
          },
          {
            "id": "161700da-37a3-47ef-8a42-2d0fa99e0a30",
            "name": "SQLite & PostgreSQL",
            "level": "Senior",
            "score": 85,
            "icon": "",
            "order": 2
          },
          {
            "id": "116d3fa0-3c6f-43fd-bcdd-3b5b2be7001d",
            "name": "API REST",
            "level": "Expert",
            "score": 90,
            "icon": "",
            "order": 3
          }
        ]
      },
      {
        "id": "94761afc-f248-4bc2-ba71-e807410739a0",
        "order": 2,
        "enabled": true,
        "archived": false,
        "name": "Contraintes de terrain",
        "icon": "wrench",
        "skills": [
          {
            "id": "6b3fbe27-eff7-4d32-b953-3c7ac467b42a",
            "name": "Synchronisation différée",
            "level": "Expert",
            "score": 93,
            "icon": "",
            "order": 0
          },
          {
            "id": "24f8c138-798f-40cc-9c94-243d27916cad",
            "name": "Optimisation basse bande passante",
            "level": "Expert",
            "score": 91,
            "icon": "",
            "order": 1
          },
          {
            "id": "92ed6626-6377-4f2b-ac10-120b79dac1d7",
            "name": "Passerelles SMS / USSD",
            "level": "Senior",
            "score": 78,
            "icon": "",
            "order": 2
          },
          {
            "id": "1397acf9-8fe8-48b6-9905-6b2e9e25b9cd",
            "name": "Déploiement sur serveur local",
            "level": "Senior",
            "score": 80,
            "icon": "",
            "order": 3
          }
        ]
      }
    ]
  },
  "projects": {
    "enabled": true,
    "title": "Projets",
    "subtitle": "Une sélection de ce dont je suis le plus fier",
    "items": [
      {
        "id": "e6d8d190-d97d-435e-a409-04646a497208",
        "order": 0,
        "enabled": true,
        "archived": false,
        "title": "Coordination humanitaire hors ligne",
        "description": "Outil de suivi des distributions pour un collectif d'ONG. Les équipes saisissent sur le terrain sans réseau ; les données se synchronisent au retour à Bangui.",
        "longDescription": "",
        "image": "",
        "video": "",
        "technologies": [
          "Vue 3",
          "TypeScript",
          "IndexedDB",
          "Node.js",
          "PostgreSQL"
        ],
        "demoUrl": "",
        "repoUrl": "",
        "startDate": "2023-02-01",
        "endDate": "2024-08-01",
        "kind": "client",
        "tags": [
          "hors-ligne",
          "humanitaire"
        ],
        "featured": true
      },
      {
        "id": "598b80aa-9284-4971-8f68-7c59aceb26c5",
        "order": 1,
        "enabled": true,
        "archived": false,
        "title": "Gestion pour coopérative agricole",
        "description": "Suivi des livraisons et des paiements pour une coopérative caféière de la Lobaye. Interface en français et en sango, utilisable sur téléphone à petit écran.",
        "longDescription": "",
        "image": "",
        "video": "",
        "technologies": [
          "Vue 3",
          "Laravel",
          "MySQL"
        ],
        "demoUrl": "",
        "repoUrl": "",
        "startDate": "2022-04-01",
        "endDate": "2023-01-01",
        "kind": "client",
        "tags": [
          "agriculture",
          "mobile"
        ],
        "featured": true
      },
      {
        "id": "16b46bca-52f8-4437-8cf1-a436fdd4dcd2",
        "order": 2,
        "enabled": true,
        "archived": false,
        "title": "Portail de préinscription universitaire",
        "description": "Préinscription en ligne pour une faculté de Bangui : 4 000 dossiers traités sur la première rentrée, contre des files d'attente de plusieurs jours auparavant.",
        "longDescription": "",
        "image": "",
        "video": "",
        "technologies": [
          "Vue 3",
          "Node.js",
          "PostgreSQL",
          "Docker"
        ],
        "demoUrl": "",
        "repoUrl": "",
        "startDate": "2021-05-01",
        "endDate": "2021-11-01",
        "kind": "client",
        "tags": [
          "éducation",
          "web"
        ],
        "featured": false
      },
      {
        "id": "3f086620-4f4e-48f2-be09-68422454a58c",
        "order": 3,
        "enabled": true,
        "archived": false,
        "title": "Composants légers pour connexion lente",
        "description": "Bibliothèque Vue de composants pesant moins de 15 Ko au total, conçus pour des pages qui s'affichent en 2G. Utilisée par plusieurs équipes en Afrique centrale.",
        "longDescription": "",
        "image": "",
        "video": "",
        "technologies": [
          "Vue 3",
          "TypeScript",
          "Vite"
        ],
        "demoUrl": "",
        "repoUrl": "https://github.com",
        "startDate": "2020-06-01",
        "endDate": "",
        "kind": "open-source",
        "tags": [
          "open-source",
          "performance"
        ],
        "featured": false
      }
    ]
  },
  "experience": {
    "enabled": true,
    "title": "Expérience",
    "subtitle": "Mon parcours professionnel",
    "items": [
      {
        "id": "cd3f1a1c-8fc1-4069-848d-cbb02d3c1220",
        "order": 0,
        "enabled": true,
        "archived": false,
        "company": "Bêafrîka Digital",
        "role": "Lead développeur",
        "location": "Bangui",
        "startDate": "2021-04",
        "endDate": "",
        "current": true,
        "description": "Je pilote l'architecture technique de l'agence et j'encadre une équipe de quatre développeurs.",
        "achievements": [
          "Mise en place du fonctionnement hors ligne sur six applications clientes",
          "Poids moyen des pages réduit de 1,8 Mo à 240 Ko",
          "Programme interne de formation : douze développeurs juniors accompagnés"
        ],
        "technologies": [
          "Vue 3",
          "TypeScript",
          "Node.js",
          "Docker"
        ],
        "logo": ""
      },
      {
        "id": "a422d786-1360-4852-92af-1c43fc5b0f15",
        "order": 1,
        "enabled": true,
        "archived": false,
        "company": "Oubangui Solutions",
        "role": "Développeur full-stack",
        "location": "Bangui",
        "startDate": "2018-09",
        "endDate": "2021-03",
        "current": false,
        "description": "Développement d'applications de gestion pour des ONG et des administrations centrafricaines.",
        "achievements": [
          "Portail de préinscription universitaire, 4 000 dossiers la première année",
          "Migration de trois applications vers une architecture synchronisable"
        ],
        "technologies": [
          "Vue 2",
          "Laravel",
          "MySQL"
        ],
        "logo": ""
      },
      {
        "id": "aff39f52-fd00-472c-81df-fb88129e3df1",
        "order": 2,
        "enabled": true,
        "archived": false,
        "company": "Indépendant",
        "role": "Développeur web",
        "location": "Bangui",
        "startDate": "2016-01",
        "endDate": "2018-08",
        "current": false,
        "description": "Sites vitrines et petits outils de gestion pour des commerces et associations de Bangui.",
        "achievements": [
          "Une vingtaine de projets livrés",
          "Formation des clients à leur propre outil"
        ],
        "technologies": [
          "PHP",
          "JavaScript",
          "MySQL"
        ],
        "logo": ""
      }
    ]
  },
  "education": {
    "enabled": true,
    "title": "Formation",
    "subtitle": "",
    "items": [
      {
        "id": "72afac76-0c11-4748-8434-97e82259963b",
        "order": 0,
        "enabled": true,
        "archived": false,
        "school": "Université de Bangui",
        "degree": "Licence",
        "field": "Informatique",
        "startYear": "2013",
        "endYear": "2016",
        "description": "Spécialisation en génie logiciel et bases de données.",
        "logo": ""
      },
      {
        "id": "8bdfa831-6de3-4263-ad43-9abf748b0d6d",
        "order": 1,
        "enabled": true,
        "archived": false,
        "school": "Lycée Barthélemy Boganda",
        "degree": "Baccalauréat",
        "field": "Série C — Mathématiques et sciences physiques",
        "startYear": "2010",
        "endYear": "2013",
        "description": "",
        "logo": ""
      }
    ]
  },
  "testimonials": {
    "enabled": true,
    "title": "Témoignages",
    "subtitle": "Ce qu'en disent celles et ceux avec qui j'ai travaillé",
    "items": [
      {
        "id": "2cd3d2bf-0a24-405b-ab24-04167260b25b",
        "order": 0,
        "enabled": true,
        "archived": false,
        "name": "Nadège Sepou",
        "role": "Coordinatrice programmes",
        "company": "Collectif humanitaire Ouham",
        "photo": "",
        "quote": "Nos équipes travaillent dans des zones sans réseau. Landry est le premier à nous avoir proposé un outil qui en tient compte au lieu de nous demander de nous adapter.",
        "rating": 5
      },
      {
        "id": "af0a258b-204b-4b0b-a12b-aebd128c9ab7",
        "order": 1,
        "enabled": true,
        "archived": false,
        "name": "Clotaire Zoumara",
        "role": "Directeur technique",
        "company": "Bêafrîka Digital",
        "photo": "",
        "quote": "Il ne livre jamais une fonctionnalité sans l'avoir testée sur un téléphone bas de gamme en 2G. Ça paraît évident, presque personne ne le fait.",
        "rating": 5
      },
      {
        "id": "57053c2c-b98b-4709-a475-676dec245614",
        "order": 2,
        "enabled": true,
        "archived": false,
        "name": "Prisca Ndoto",
        "role": "Présidente",
        "company": "Coopérative caféière de la Lobaye",
        "photo": "",
        "quote": "Nos membres ne sont pas informaticiens. Ils utilisent l'application depuis deux ans sans jamais nous appeler à l'aide. C'est la meilleure preuve.",
        "rating": 5
      }
    ]
  },
  "articles": {
    "enabled": false,
    "title": "Articles",
    "subtitle": "",
    "items": []
  },
  "timeline": {
    "enabled": true,
    "title": "Parcours",
    "subtitle": "Les étapes qui comptent",
    "items": [
      {
        "id": "8f0c7925-6004-4fc7-bebe-3467b8281ca3",
        "order": 0,
        "enabled": true,
        "archived": false,
        "date": "2016",
        "title": "Premiers clients à Bangui",
        "description": "Licence en poche, premiers sites pour des commerces du centre-ville.",
        "icon": ""
      },
      {
        "id": "3f808fa9-027a-4839-98bd-130b3b0ea43b",
        "order": 1,
        "enabled": true,
        "archived": false,
        "date": "2018",
        "title": "Entrée chez Oubangui Solutions",
        "description": "Passage aux projets institutionnels et humanitaires.",
        "icon": ""
      },
      {
        "id": "40e1e770-8bd7-4188-8e9a-de016296982f",
        "order": 2,
        "enabled": true,
        "archived": false,
        "date": "2021",
        "title": "Lead développeur",
        "description": "Responsabilité d'architecture et encadrement d'équipe.",
        "icon": ""
      },
      {
        "id": "95167101-3971-4715-9987-5e8df6b8dbec",
        "order": 3,
        "enabled": true,
        "archived": false,
        "date": "2024",
        "title": "Formation de la relève",
        "description": "Plus de soixante développeurs formés en Afrique centrale.",
        "icon": ""
      }
    ]
  },
  "gallery": {
    "enabled": false,
    "title": "Galerie",
    "subtitle": "",
    "items": []
  },
  "contact": {
    "enabled": true,
    "title": "Contact",
    "subtitle": "Un projet, une question, ou juste envie d'échanger ?",
    "email": "landry.kongbo@exemple.cf",
    "phone": "+236 72 45 18 90",
    "address": "Bangui, République centrafricaine",
    "mapEmbed": "",
    "formEnabled": true,
    "socialLinks": [
      {
        "id": "4a7702bf-c044-4fa4-b176-f7b973dbfffd",
        "order": 0,
        "enabled": true,
        "archived": false,
        "platform": "GitHub",
        "url": "https://github.com",
        "icon": "github"
      },
      {
        "id": "3df68891-df1f-4031-8560-f02dbea9c559",
        "order": 1,
        "enabled": true,
        "archived": false,
        "platform": "LinkedIn",
        "url": "https://linkedin.com",
        "icon": "briefcase"
      },
      {
        "id": "867c13fd-66c4-455a-a692-55c4d48bac8a",
        "order": 2,
        "enabled": true,
        "archived": false,
        "platform": "WhatsApp",
        "url": "https://wa.me/23672451890",
        "icon": "message-circle"
      }
    ]
  },
  "customSections": [
    {
      "id": "0a5d5a48-7b8f-4fe5-aee7-2fcdce5bef39",
      "name": "Certifications",
      "slug": "certifications",
      "icon": "award",
      "enabled": true,
      "order": 0,
      "layout": "cards",
      "fields": [
        {
          "name": "nom",
          "label": "Certification",
          "type": "text",
          "required": true,
          "role": "title"
        },
        {
          "name": "organisme",
          "label": "Organisme",
          "type": "text",
          "required": true,
          "role": "subtitle"
        },
        {
          "name": "date",
          "label": "Date d'obtention",
          "type": "date",
          "required": false
        },
        {
          "name": "lien",
          "label": "Vérifier",
          "type": "url",
          "required": false,
          "role": "link"
        }
      ],
      "items": [
        {
          "id": "fa78d8ef-13c9-45d0-a808-e94164050cdb",
          "order": 0,
          "enabled": true,
          "archived": false,
          "data": {
            "nom": "Développement web progressif (PWA)",
            "organisme": "Google Africa Developer Scholarship",
            "date": "2022-11-18",
            "lien": ""
          },
          "createdAt": "2026-07-21T20:42:33.982Z",
          "updatedAt": "2026-07-21T20:42:33.982Z"
        },
        {
          "id": "24db177c-1ad8-41dd-97b1-cdf114d58837",
          "order": 1,
          "enabled": true,
          "archived": false,
          "data": {
            "nom": "Gestion de données humanitaires",
            "organisme": "OCHA — Bureau régional Afrique centrale",
            "date": "2023-06-05",
            "lien": ""
          },
          "createdAt": "2026-07-21T20:42:33.983Z",
          "updatedAt": "2026-07-21T20:42:33.983Z"
        }
      ]
    }
  ],
  "design": {
    "active": "dark-matter",
    "autoRotate": true,
    "schedule": {
      "1": "neon-pulse",
      "2": "minimalist-white",
      "3": "dark-matter",
      "4": "glassmorphism",
      "5": "gradient-flow",
      "6": "retro-wave",
      "7": "nature-organic",
      "8": "tech-blue",
      "9": "art-deco",
      "10": "sakura",
      "11": "corporate-pro",
      "12": "futuristic"
    },
    "customColors": {},
    "customTypography": {},
    "customCss": "",
    "animationSpeed": 1,
    "animationsEnabled": true
  },
  "seo": {
    "title": "Landry Kongbo — Développeur Full-Stack à Bangui",
    "description": "Portfolio de Landry Kongbo, développeur full-stack basé à Bangui. Applications web hors ligne et optimisées pour les connexions lentes. Vue.js, TypeScript, Node.js.",
    "keywords": "développeur, full-stack, bangui, centrafrique, vue.js, typescript, node.js, hors-ligne, pwa",
    "ogImage": "",
    "author": "Landry Kongbo",
    "siteUrl": ""
  },
  "analytics": {
    "googleAnalyticsId": "",
    "enableTracking": false
  },
  "engagement": {
    "likesEnabled": true,
    "commentsEnabled": true,
    "ratingsEnabled": true,
    "commentsModerated": true,
    "likeCountPublic": false
  },
  "branding": {
    "logo": "",
    "favicon": "",
    "footerText": "Construit à Bangui, avec soin et pour durer."
  }
}
